instiz/CONSTANTS.py
instiz/__init__.py
instiz/helper.py
instiz/ichart.py
instiz/models/__init__.py
instiz/models/artist.py
instiz/models/entry.py
tests/__init__.py
tests/test_artist_entry.py
tests/test_helper.py
tests/test_ichart.py
instiz-0.2.1.dist-info/LICENSE
instiz-0.2.1.dist-info/METADATA
instiz-0.2.1.dist-info/WHEEL
instiz-0.2.1.dist-info/top_level.txt
instiz-0.2.1.dist-info/RECORD
