Metadata-Version: 2.1
Name: instiz
Version: 0.2.1
Summary: A Python3-only library for iChart K-Pop chart scores.
Home-page: https://github.com/Chromadream/instiz
Author: Jonathan Nicholas
Author-email: Jonathan.Nicholas@protonmail.com
License: UNKNOWN
Platform: UNKNOWN
Classifier: Programming Language :: Python :: 3
Classifier: License :: OSI Approved :: MIT License
Classifier: Operating System :: OS Independent
Classifier: Development Status :: 4 - Beta
Classifier: Topic :: Utilities
Classifier: Topic :: Software Development :: Libraries
Requires-Dist: requests (>=2.20.0)
Requires-Dist: beautifulsoup4 (>=4.6.3)
Requires-Dist: attrs (>=18.2.0)
Requires-Dist: lxml (>=4.2.5)
